ap_gym/__init__.py
ap_gym/active_classification_env.py
ap_gym/active_perception_env.py
ap_gym/active_perception_vector_env.py
ap_gym/active_regression_env.py
ap_gym/image_space.py
ap_gym/loss_fn.py
ap_gym/time_limit.py
ap_gym/types.py
ap_gym/util.py
ap_gym/vector_to_single_wrapper.py
ap_gym/envs/__init__.py
ap_gym/envs/image_classification.py
ap_gym/envs/image_localization.py
ap_gym/envs/lidar_localization2d.py
ap_gym/envs/light_dark.py
ap_gym/envs/registration.py
ap_gym/envs/style.py
ap_gym/envs/dataset/__init__.py
ap_gym/envs/dataset/buffered_iterator.py
ap_gym/envs/dataset/data_loader.py
ap_gym/envs/dataset/dataset.py
ap_gym/envs/dataset/dataset_iterator.py
ap_gym/envs/floor_map/__init__.py
ap_gym/envs/floor_map/floor_map_dataset.py
ap_gym/envs/floor_map/floor_map_dataset_maze.py
ap_gym/envs/floor_map/floor_map_dataset_rooms.py
ap_gym/envs/image/__init__.py
ap_gym/envs/image/circle_square_dataset.py
ap_gym/envs/image/huggingface_image_classification_dataset.py
ap_gym/envs/image/image_classification_dataset.py
ap_gym/envs/image/image_perception_module.py
ap_gym/tools/__init__.py
ap_gym/tools/create_env_vid.py
ap_gym-0.3.0.dist-info/licenses/LICENSE
ap_gym-0.3.0.dist-info/METADATA
ap_gym-0.3.0.dist-info/WHEEL
ap_gym-0.3.0.dist-info/entry_points.txt
ap_gym-0.3.0.dist-info/top_level.txt
ap_gym-0.3.0.dist-info/RECORD
