Metadata-Version: 2.4
Name: ap_gym
Version: 0.3.0
Summary: Active Perception Gym: extension of Gymnasium for active perception tasks.
Author-email: Tim Schneider <tim@robot-learning.de>
License: MIT
Project-URL: homepage, https://github.com/TimSchneider42/active-perception-gym
License-File: LICENSE
Requires-Dist: gymnasium>=1.1.0
Requires-Dist: scipy
Requires-Dist: numpy
Requires-Dist: datasets
Requires-Dist: shapely
Provides-Extra: examples
Requires-Dist: matplotlib; extra == "examples"
Dynamic: license-file
